{
  "uuid": "1fc8d2b4-2c3e-406d-baa0-a3045164595c",
  "starterPrompted": true,
  "starterLocked": false,
  "starterSelected": true,
  "starterUUID": "b6ae6123-a5cc-45f0-979d-0cddde82c12c",
  "keyItems": [],
  "battleTheme": "cobblemon:battle.pvp.default",
  "extraData": {
    "cobbledex_discovery": {
      "registers": {
        "snivy": {
          "normal": {
            "isShiny": false,
            "status": "CAUGHT",
            "discoveredTimestamp": 1739300674820,
            "caughtTimestamp": 1739300674820
          }
        },
        "drilbur": {
          "normal": {
            "isShiny": false,
            "status": "CAUGHT",
            "discoveredTimestamp": 1739300848879,
            "caughtTimestamp": 1739300848879
          }
        },
        "servine": {
          "normal": {
            "isShiny": false,
            "status": "CAUGHT",
            "discoveredTimestamp": 1739302892856,
            "caughtTimestamp": 1739302892856
          }
        },
        "serperior": {
          "normal": {
            "isShiny": false,
            "status": "CAUGHT",
            "discoveredTimestamp": 1739302904056,
            "caughtTimestamp": 1739302904056
          }
        },
        "honedge": {
          "normal": {
            "isShiny": false,
            "status": "CAUGHT",
            "discoveredTimestamp": 1739304635277,
            "caughtTimestamp": 1739304635277
          }
        },
        "misdreavus": {
          "normal": {
            "isShiny": false,
            "status": "SEEN",
            "discoveredTimestamp": 1739304816327
          }
        },
        "phantump": {
          "normal": {
            "isShiny": false,
            "status": "SEEN",
            "discoveredTimestamp": 1739304867251
          }
        },
        "paras": {
          "normal": {
            "isShiny": false,
            "status": "SEEN",
            "discoveredTimestamp": 1739304877779
          }
        },
        "gastly": {
          "normal": {
            "isShiny": false,
            "status": "CAUGHT",
            "discoveredTimestamp": 1739304920431,
            "caughtTimestamp": 1739304942117
          }
        },
        "spinarak": {
          "normal": {
            "isShiny": false,
            "status": "SEEN",
            "discoveredTimestamp": 1739304989106
          }
        },
        "kakuna": {
          "normal": {
            "isShiny": false,
            "status": "SEEN",
            "discoveredTimestamp": 1739305091965
          }
        },
        "fletchinder": {
          "normal": {
            "isShiny": false,
            "status": "CAUGHT",
            "discoveredTimestamp": 1739305167775,
            "caughtTimestamp": 1739305245376
          }
        },
        "talonflame": {
          "normal": {
            "isShiny": false,
            "status": "CAUGHT",
            "discoveredTimestamp": 1739305257834,
            "caughtTimestamp": 1739305257834
          }
        },
        "galvantula": {
          "normal": {
            "isShiny": false,
            "status": "SEEN",
            "discoveredTimestamp": 1739305272806
          }
        },
        "blipbug": {
          "normal": {
            "isShiny": false,
            "status": "SEEN",
            "discoveredTimestamp": 1739305305578
          }
        },
        "weedle": {
          "normal": {
            "isShiny": false,
            "status": "SEEN",
            "discoveredTimestamp": 1739305313796
          }
        },
        "metapod": {
          "normal": {
            "isShiny": false,
            "status": "SEEN",
            "discoveredTimestamp": 1739305796214
          }
        },
        "bouffalant": {
          "normal": {
            "isShiny": false,
            "status": "SEEN",
            "discoveredTimestamp": 1739305990456
          }
        },
        "haunter": {
          "normal": {
            "isShiny": false,
            "status": "CAUGHT",
            "discoveredTimestamp": 1739306343581,
            "caughtTimestamp": 1739306343581
          }
        },
        "gengar": {
          "normal": {
            "isShiny": false,
            "status": "CAUGHT",
            "discoveredTimestamp": 1739306378402,
            "caughtTimestamp": 1739306378402
          }
        },
        "shedinja": {
          "normal": {
            "isShiny": false,
            "status": "SEEN",
            "discoveredTimestamp": 1739307048278
          }
        },
        "zorua": {
          "normal": {
            "isShiny": false,
            "status": "CAUGHT",
            "discoveredTimestamp": 1739307058176,
            "caughtTimestamp": 1739307195477
          }
        },
        "growlithe": {
          "normal": {
            "isShiny": false,
            "status": "CAUGHT",
            "discoveredTimestamp": 1739309307472,
            "caughtTimestamp": 1739309307472
          }
        },
        "magikarp": {
          "normal": {
            "isShiny": false,
            "status": "CAUGHT",
            "discoveredTimestamp": 1739310887994,
            "caughtTimestamp": 1739310887994
          }
        },
        "gyarados": {
          "normal": {
            "isShiny": false,
            "status": "CAUGHT",
            "discoveredTimestamp": 1739310920934,
            "caughtTimestamp": 1739310920934
          }
        },
        "charmeleon": {
          "normal": {
            "isShiny": false,
            "status": "CAUGHT",
            "discoveredTimestamp": 1739313287505,
            "caughtTimestamp": 1739313287505
          }
        },
        "darumaka": {
          "normal": {
            "isShiny": false,
            "status": "SEEN",
            "discoveredTimestamp": 1739314342007
          }
        },
        "cubone": {
          "normal": {
            "isShiny": false,
            "status": "CAUGHT",
            "discoveredTimestamp": 1739314490191,
            "caughtTimestamp": 1739314490191
          }
        },
        "slugma": {
          "normal": {
            "isShiny": false,
            "status": "SEEN",
            "discoveredTimestamp": 1739315588994
          }
        },
        "ponyta": {
          "normal": {
            "isShiny": false,
            "status": "SEEN",
            "discoveredTimestamp": 1739316357933
          },
          "galar": {
            "isShiny": false,
            "status": "SEEN",
            "discoveredTimestamp": 1739325384248
          }
        },
        "magmar": {
          "normal": {
            "isShiny": false,
            "status": "SEEN",
            "discoveredTimestamp": 1739316806611
          }
        },
        "zeraora": {
          "normal": {
            "isShiny": false,
            "status": "CAUGHT",
            "discoveredTimestamp": 1739319580922,
            "caughtTimestamp": 1739319580922
          }
        },
        "doublade": {
          "normal": {
            "isShiny": false,
            "status": "CAUGHT",
            "discoveredTimestamp": 1739319778936,
            "caughtTimestamp": 1739319778936
          }
        },
        "tauros": {
          "paldeablaze": {
            "isShiny": false,
            "status": "SEEN",
            "discoveredTimestamp": 1739319886568
          }
        },
        "pyroar": {
          "normal": {
            "isShiny": false,
            "status": "SEEN",
            "discoveredTimestamp": 1739320058421
          }
        },
        "capsakid": {
          "normal": {
            "isShiny": false,
            "status": "SEEN",
            "discoveredTimestamp": 1739320284924
          }
        },
        "dodrio": {
          "normal": {
            "isShiny": false,
            "status": "SEEN",
            "discoveredTimestamp": 1739320289726
          }
        },
        "klink": {
          "normal": {
            "isShiny": false,
            "status": "SEEN",
            "discoveredTimestamp": 1739321009326
          }
        },
        "roggenrola": {
          "normal": {
            "isShiny": false,
            "status": "SEEN",
            "discoveredTimestamp": 1739321016728
          }
        },
        "zubat": {
          "normal": {
            "isShiny": false,
            "status": "SEEN",
            "discoveredTimestamp": 1739321335653
          }
        },
        "lillipup": {
          "normal": {
            "isShiny": false,
            "status": "SEEN",
            "discoveredTimestamp": 1739321415502
          }
        },
        "shuppet": {
          "normal": {
            "isShiny": false,
            "status": "SEEN",
            "discoveredTimestamp": 1739321629549
          }
        },
        "aegislash": {
          "normal": {
            "isShiny": false,
            "status": "CAUGHT",
            "discoveredTimestamp": 1739321988792,
            "caughtTimestamp": 1739321988792
          }
        },
        "rattata": {
          "alola": {
            "isShiny": false,
            "status": "SEEN",
            "discoveredTimestamp": 1739322220243
          }
        },
        "diglett": {
          "alola": {
            "isShiny": false,
            "status": "SEEN",
            "discoveredTimestamp": 1739322235606
          }
        },
        "xerneas": {
          "normal": {
            "isShiny": false,
            "status": "CAUGHT",
            "discoveredTimestamp": 1739322958622,
            "caughtTimestamp": 1739322958622
          }
        },
        "ariados": {
          "normal": {
            "isShiny": false,
            "status": "SEEN",
            "discoveredTimestamp": 1739323098770
          }
        },
        "drifloon": {
          "normal": {
            "isShiny": false,
            "status": "SEEN",
            "discoveredTimestamp": 1739323176150
          }
        },
        "bunnelby": {
          "normal": {
            "isShiny": false,
            "status": "SEEN",
            "discoveredTimestamp": 1739323289308
          }
        },
        "pichu": {
          "normal": {
            "isShiny": false,
            "status": "CAUGHT",
            "discoveredTimestamp": 1739323401150,
            "caughtTimestamp": 1739323401150
          }
        },
        "spiritomb": {
          "normal": {
            "isShiny": false,
            "status": "CAUGHT",
            "discoveredTimestamp": 1739324722347,
            "caughtTimestamp": 1739324795386
          }
        },
        "banette": {
          "normal": {
            "isShiny": false,
            "status": "SEEN",
            "discoveredTimestamp": 1739325028947
          }
        },
        "buneary": {
          "normal": {
            "isShiny": false,
            "status": "SEEN",
            "discoveredTimestamp": 1739325382746
          }
        },
        "ledyba": {
          "normal": {
            "isShiny": false,
            "status": "SEEN",
            "discoveredTimestamp": 1739325430445
          }
        },
        "lopunny": {
          "normal": {
            "isShiny": false,
            "status": "CAUGHT",
            "discoveredTimestamp": 1739325580793,
            "caughtTimestamp": 1739325596985
          }
        },
        "zigzagoon": {
          "normal": {
            "isShiny": false,
            "status": "SEEN",
            "discoveredTimestamp": 1739366984381
          }
        },
        "golem": {
          "normal": {
            "isShiny": false,
            "status": "SEEN",
            "discoveredTimestamp": 1739367071636
          }
        },
        "fletchling": {
          "normal": {
            "isShiny": false,
            "status": "SEEN",
            "discoveredTimestamp": 1739367693140
          }
        },
        "onix": {
          "normal": {
            "isShiny": false,
            "status": "CAUGHT",
            "discoveredTimestamp": 1739368362837,
            "caughtTimestamp": 1739368404823
          }
        },
        "glimmet": {
          "normal": {
            "isShiny": false,
            "status": "SEEN",
            "discoveredTimestamp": 1739368411235
          }
        },
        "joltik": {
          "normal": {
            "isShiny": false,
            "status": "SEEN",
            "discoveredTimestamp": 1739369477969
          }
        },
        "linoone": {
          "normal": {
            "isShiny": false,
            "status": "SEEN",
            "discoveredTimestamp": 1739370469626
          }
        },
        "slowbro": {
          "normal": {
            "isShiny": false,
            "status": "SEEN",
            "discoveredTimestamp": 1739370668680
          }
        },
        "tinkatink": {
          "normal": {
            "isShiny": false,
            "status": "SEEN",
            "discoveredTimestamp": 1739370698020
          }
        },
        "staraptor": {
          "normal": {
            "isShiny": false,
            "status": "CAUGHT",
            "discoveredTimestamp": 1739371391671,
            "caughtTimestamp": 1739371449421
          }
        },
        "geodude": {
          "normal": {
            "isShiny": false,
            "status": "SEEN",
            "discoveredTimestamp": 1739373316837
          }
        },
        "sizzlipede": {
          "normal": {
            "isShiny": false,
            "status": "SEEN",
            "discoveredTimestamp": 1739374094774
          }
        },
        "centiskorch": {
          "normal": {
            "isShiny": false,
            "status": "SEEN",
            "discoveredTimestamp": 1739374646135
          }
        },
        "larvesta": {
          "normal": {
            "isShiny": false,
            "status": "CAUGHT",
            "discoveredTimestamp": 1739376220591,
            "caughtTimestamp": 1739376220591
          }
        },
        "ninjask": {
          "normal": {
            "isShiny": false,
            "status": "SEEN",
            "discoveredTimestamp": 1739380463315
          }
        },
        "taillow": {
          "normal": {
            "isShiny": false,
            "status": "SEEN",
            "discoveredTimestamp": 1739380476862
          }
        },
        "gossifleur": {
          "normal": {
            "isShiny": false,
            "status": "SEEN",
            "discoveredTimestamp": 1739380544842
          }
        },
        "volcarona": {
          "normal": {
            "isShiny": false,
            "status": "CAUGHT",
            "discoveredTimestamp": 1739380596662,
            "caughtTimestamp": 1739380596662
          }
        },
        "zygarde": {
          "normal": {
            "isShiny": false,
            "status": "SEEN",
            "discoveredTimestamp": 1739382379732
          }
        },
        "hydreigon": {
          "normal": {
            "isShiny": false,
            "status": "SEEN",
            "discoveredTimestamp": 1739382390420
          }
        },
        "charizard": {
          "normal": {
            "isShiny": false,
            "status": "SEEN",
            "discoveredTimestamp": 1739382394764
          }
        }
      },
      "name": "cobbledex_discovery"
    },
    "Cobbledex_RewardHistory": {
      "received": [
        "1",
        "2",
        "3",
        "4",
        "5",
        "6",
        "7",
        "8",
        "9",
        "10",
        "11",
        "12",
        "13",
        "14",
        "15",
        "16",
        "17",
        "18",
        "19",
        "20",
        "21",
        "121",
        "22",
        "23",
        "24",
        "25",
        "26",
        "27"
      ],
      "name": "Cobbledex_RewardHistory"
    },
    "captureCount": {
      "name": "captureCount",
      "defeats": {
        "snivy": 1,
        "drilbur": 1,
        "servine": 1,
        "serperior": 1,
        "honedge": 1,
        "gastly": 1,
        "fletchinder": 1,
        "talonflame": 1,
        "haunter": 1,
        "gengar": 1,
        "zorua": 1,
        "growlithe": 1,
        "magikarp": 1,
        "gyarados": 2,
        "charmeleon": 1,
        "cubone": 1,
        "zeraora": 1,
        "doublade": 1,
        "aegislash": 1,
        "xerneas": 1,
        "pichu": 1,
        "spiritomb": 1,
        "lopunny": 1,
        "onix": 1,
        "staraptor": 1,
        "larvesta": 1,
        "volcarona": 1
      }
    },
    "yacb$boostManager": {
      "name": "yacb$boostManager",
      "manager": {
        "shinyBoost": {
          "active": false,
          "amplifier": 0.0,
          "ticksRemain": 0
        },
        "speciesWeightBoosts": {},
        "labelWeightBoosts": {},
        "endedBoosts": [],
        "shouldSave": true,
        "saveTimer": 1200
      }
    },
    "koStreak": {
      "name": "koStreak",
      "species": "gimmighoul",
      "count": 1
    },
    "koCount": {
      "name": "koCount",
      "defeats": {
        "bunnelby": 1,
        "sentret": 1,
        "tinkatink": 1,
        "gimmighoul": 3,
        "weedle": 1,
        "ponyta": 2
      }
    },
    "captureStreak": {
      "name": "captureStreak",
      "species": "larvesta",
      "count": 1
    },
    "encounter": {
      "name": "encounter",
      "encounters": {
        "snivy": true,
        "drilbur": true,
        "bunnelby": true,
        "sentret": true,
        "servine": true,
        "serperior": true,
        "tinkatink": true,
        "gimmighoul": true,
        "honedge": true,
        "gastly": true,
        "weedle": true,
        "fletchinder": true,
        "talonflame": true,
        "haunter": true,
        "gengar": true,
        "zorua": true,
        "growlithe": true,
        "magikarp": true,
        "gyarados": true,
        "charmeleon": true,
        "cubone": true,
        "ponyta": true,
        "litwick": true,
        "zeraora": true,
        "doublade": true,
        "tauros": true,
        "shuppet": true,
        "aegislash": true,
        "xerneas": true,
        "pichu": true,
        "spiritomb": true,
        "lopunny": true,
        "onix": true,
        "staraptor": true,
        "larvesta": true,
        "volcarona": true
      }
    },
    "cobblenavPlayerStatsData": {
      "name": "cobblenavPlayerStatsData",
      "totalPvpCount": 0,
      "startDate": 1739300674820,
      "grantedBadges": [],
      "pokemonUsage": {
        "cf0c8be1-5e56-43fe-ad3c-1b4ebb7a57df": 8,
        "f8981f5d-4315-4f02-83df-d719a0d79297": 9,
        "2c5c534e-231f-420f-89c9-5411109c19d2": 1,
        "a8caf8a2-3b7f-4fb7-9400-05d6a1da92da": 11,
        "0642a84e-8ab3-4e56-bea7-ab179694d571": 11,
        "7944a97f-0a75-4b4b-9316-8197deb11d69": 4,
        "5ce0a6db-e6dd-48fa-96a2-d4e5b7f8f3bd": 8,
        "b6ae6123-a5cc-45f0-979d-0cddde82c12c": 16,
        "6e989806-74ce-46bb-aa5f-ba6bf707e667": 1
      }
    }
  },
  "advancementData": {
    "totalCaptureCount": 18,
    "totalEggsHatched": 0,
    "totalEvolvedCount": 9,
    "totalBattleVictoryCount": 13,
    "totalPvPBattleVictoryCount": 0,
    "totalPvWBattleVictoryCount": 13,
    "totalPvNBattleVictoryCount": 0,
    "totalShinyCaptureCount": 0,
    "totalTradedCount": 0,
    "totalTypeCaptureCounts": {
      "ground": 3,
      "steel": 1,
      "ghost": 3,
      "poison": 1,
      "fire": 4,
      "flying": 3,
      "dark": 2,
      "water": 2,
      "electric": 2,
      "fairy": 1,
      "normal": 2,
      "rock": 1,
      "bug": 1
    },
    "totalDefeatedCounts": {
      "cobblemon:bunnelby": 1,
      "cobblemon:sentret": 1,
      "cobblemon:tinkatink": 1,
      "cobblemon:gimmighoul": 3,
      "cobblemon:weedle": 1,
      "cobblemon:ponyta": 2
    },
    "aspectsCollected": {}
  }
}